[
    {
        "LootLimitID": "ORGypsum",
        "IsReplicated": false,
        "MinLimitSeconds": 840,
        "MaxLimitSeconds": 900,
        "CountLimit": 2,
        "MinLimitMult": 100,
        "MaxLimitMult": 100,
        "LimitExpireSeconds": 64800,
        "LootTagValuePerCount": null,
        "LootTagValueOverrideAtLimit": "",
        "LimitNotificationLocTag": ""
    },
    {
        "LootLimitID": "GypsumBlue",
        "IsReplicated": false,
        "MinLimitSeconds": 170,
        "MaxLimitSeconds": 180,
        "CountLimit": 2,
        "MinLimitMult": 400,
        "MaxLimitMult": 400,
        "LimitExpireSeconds": 64800,
        "LootTagValuePerCount": null,
        "LootTagValueOverrideAtLimit": "",
        "LimitNotificationLocTag": ""
    },
    {
        "LootLimitID": "PostCapGypsum",
        "IsReplicated": false,
        "MinLimitSeconds": 3500,
        "MaxLimitSeconds": 3600,
        "CountLimit": 1,
        "MinLimitMult": 20,
        "MaxLimitMult": 20,
        "LimitExpireSeconds": 64800,
        "LootTagValuePerCount": null,
        "LootTagValueOverrideAtLimit": "",
        "LimitNotificationLocTag": ""
    },
    {
        "LootLimitID": "GypsumBlack",
        "IsReplicated": false,
        "MinLimitSeconds": 300,
        "MaxLimitSeconds": 390,
        "CountLimit": 3,
        "MinLimitMult": 120,
        "MaxLimitMult": 120,
        "LimitExpireSeconds": 64800,
        "LootTagValuePerCount": null,
        "LootTagValueOverrideAtLimit": "",
        "LimitNotificationLocTag": ""
    },
    {
        "LootLimitID": "GypsumYellow",
        "IsReplicated": false,
        "MinLimitSeconds": 0,
        "MaxLimitSeconds": 0,
        "CountLimit": 10,
        "MinLimitMult": 64800,
        "MaxLimitMult": 64800,
        "LimitExpireSeconds": 64800,
        "LootTagValuePerCount": null,
        "LootTagValueOverrideAtLimit": "",
        "LimitNotificationLocTag": ""
    },
    {
        "LootLimitID": "ArenaGypsum",
        "IsReplicated": false,
        "MinLimitSeconds": 3500,
        "MaxLimitSeconds": 3600,
        "CountLimit": 1,
        "MinLimitMult": 20,
        "MaxLimitMult": 20,
        "LimitExpireSeconds": 64800,
        "LootTagValuePerCount": null,
        "LootTagValueOverrideAtLimit": "",
        "LimitNotificationLocTag": ""
    },
    {
        "LootLimitID": "BreachGypsum",
        "IsReplicated": false,
        "MinLimitSeconds": 30,
        "MaxLimitSeconds": 30,
        "CountLimit": 7,
        "MinLimitMult": 64800,
        "MaxLimitMult": 64800,
        "LimitExpireSeconds": 64800,
        "LootTagValuePerCount": null,
        "LootTagValueOverrideAtLimit": "",
        "LimitNotificationLocTag": ""
    },
    {
        "LootLimitID": "WCGoldLockboxT1",
        "IsReplicated": false,
        "MinLimitSeconds": 0,
        "MaxLimitSeconds": 0,
        "CountLimit": 3,
        "MinLimitMult": 64800,
        "MaxLimitMult": 64800,
        "LimitExpireSeconds": 64800,
        "LootTagValuePerCount": null,
        "LootTagValueOverrideAtLimit": "",
        "LimitNotificationLocTag": ""
    },
    {
        "LootLimitID": "GypsumGreen",
        "IsReplicated": false,
        "MinLimitSeconds": 0,
        "MaxLimitSeconds": 0,
        "CountLimit": 1,
        "MinLimitMult": 64800,
        "MaxLimitMult": 64800,
        "LimitExpireSeconds": 64800,
        "LootTagValuePerCount": null,
        "LootTagValueOverrideAtLimit": "",
        "LimitNotificationLocTag": ""
    },
    {
        "LootLimitID": "GypsumRed",
        "IsReplicated": false,
        "MinLimitSeconds": 0,
        "MaxLimitSeconds": 0,
        "CountLimit": 2,
        "MinLimitMult": 64800,
        "MaxLimitMult": 64800,
        "LimitExpireSeconds": 64800,
        "LootTagValuePerCount": null,
        "LootTagValueOverrideAtLimit": "",
        "LimitNotificationLocTag": ""
    },
    {
        "LootLimitID": "GypsumGarnet",
        "IsReplicated": false,
        "MinLimitSeconds": 0,
        "MaxLimitSeconds": 0,
        "CountLimit": 2,
        "MinLimitMult": 64800,
        "MaxLimitMult": 64800,
        "LimitExpireSeconds": 64800,
        "LootTagValuePerCount": null,
        "LootTagValueOverrideAtLimit": "",
        "LimitNotificationLocTag": ""
    },
    {
        "LootLimitID": "GypsumPurple",
        "IsReplicated": false,
        "MinLimitSeconds": 0,
        "MaxLimitSeconds": 0,
        "CountLimit": 7,
        "MinLimitMult": 64800,
        "MaxLimitMult": 64800,
        "LimitExpireSeconds": 64800,
        "LootTagValuePerCount": null,
        "LootTagValueOverrideAtLimit": "",
        "LimitNotificationLocTag": ""
    },
    {
        "LootLimitID": "GypsumOrange",
        "IsReplicated": false,
        "MinLimitSeconds": 0,
        "MaxLimitSeconds": 0,
        "CountLimit": 2,
        "MinLimitMult": 64800,
        "MaxLimitMult": 64800,
        "LimitExpireSeconds": 64800,
        "LootTagValuePerCount": null,
        "LootTagValueOverrideAtLimit": "",
        "LimitNotificationLocTag": ""
    },
    {
        "LootLimitID": "GypsumWhite",
        "IsReplicated": false,
        "MinLimitSeconds": 0,
        "MaxLimitSeconds": 0,
        "CountLimit": 6,
        "MinLimitMult": 64800,
        "MaxLimitMult": 64800,
        "LimitExpireSeconds": 64800,
        "LootTagValuePerCount": null,
        "LootTagValueOverrideAtLimit": "",
        "LimitNotificationLocTag": ""
    },
    {
        "LootLimitID": "BagofJuniperBerriesLVL1",
        "IsReplicated": false,
        "MinLimitSeconds": 0,
        "MaxLimitSeconds": 0,
        "CountLimit": 3,
        "MinLimitMult": 64800,
        "MaxLimitMult": 64800,
        "LimitExpireSeconds": 64800,
        "LootTagValuePerCount": null,
        "LootTagValueOverrideAtLimit": "",
        "LimitNotificationLocTag": ""
    },
    {
        "LootLimitID": "BagofJuniperBerriesLVL10",
        "IsReplicated": false,
        "MinLimitSeconds": 0,
        "MaxLimitSeconds": 0,
        "CountLimit": 3,
        "MinLimitMult": 64800,
        "MaxLimitMult": 64800,
        "LimitExpireSeconds": 64800,
        "LootTagValuePerCount": null,
        "LootTagValueOverrideAtLimit": "",
        "LimitNotificationLocTag": ""
    },
    {
        "LootLimitID": "BagofJuniperBerriesLVL20",
        "IsReplicated": false,
        "MinLimitSeconds": 0,
        "MaxLimitSeconds": 0,
        "CountLimit": 3,
        "MinLimitMult": 64800,
        "MaxLimitMult": 64800,
        "LimitExpireSeconds": 64800,
        "LootTagValuePerCount": null,
        "LootTagValueOverrideAtLimit": "",
        "LimitNotificationLocTag": ""
    },
    {
        "LootLimitID": "BagofJuniperBerriesLVL30",
        "IsReplicated": false,
        "MinLimitSeconds": 0,
        "MaxLimitSeconds": 0,
        "CountLimit": 3,
        "MinLimitMult": 64800,
        "MaxLimitMult": 64800,
        "LimitExpireSeconds": 64800,
        "LootTagValuePerCount": null,
        "LootTagValueOverrideAtLimit": "",
        "LimitNotificationLocTag": ""
    },
    {
        "LootLimitID": "BagofJuniperBerriesLVL40",
        "IsReplicated": false,
        "MinLimitSeconds": 0,
        "MaxLimitSeconds": 0,
        "CountLimit": 3,
        "MinLimitMult": 64800,
        "MaxLimitMult": 64800,
        "LimitExpireSeconds": 64800,
        "LootTagValuePerCount": null,
        "LootTagValueOverrideAtLimit": "",
        "LimitNotificationLocTag": ""
    },
    {
        "LootLimitID": "BagofJuniperBerriesLVL50",
        "IsReplicated": false,
        "MinLimitSeconds": 0,
        "MaxLimitSeconds": 0,
        "CountLimit": 3,
        "MinLimitMult": 64800,
        "MaxLimitMult": 64800,
        "LimitExpireSeconds": 64800,
        "LootTagValuePerCount": null,
        "LootTagValueOverrideAtLimit": "",
        "LimitNotificationLocTag": ""
    },
    {
        "LootLimitID": "BagofJuniperBerriesLVL60",
        "IsReplicated": false,
        "MinLimitSeconds": 0,
        "MaxLimitSeconds": 0,
        "CountLimit": 3,
        "MinLimitMult": 64800,
        "MaxLimitMult": 64800,
        "LimitExpireSeconds": 64800,
        "LootTagValuePerCount": null,
        "LootTagValueOverrideAtLimit": "",
        "LimitNotificationLocTag": ""
    },
    {
        "LootLimitID": "RabbitSeasonTotem",
        "IsReplicated": false,
        "MinLimitSeconds": 0,
        "MaxLimitSeconds": 0,
        "CountLimit": 5,
        "MinLimitMult": 64800,
        "MaxLimitMult": 64800,
        "LimitExpireSeconds": 64800,
        "LootTagValuePerCount": null,
        "LootTagValueOverrideAtLimit": "",
        "LimitNotificationLocTag": ""
    },
    {
        "LootLimitID": "House_HousingItem_Storage_T4_ChestRabbit",
        "IsReplicated": false,
        "MinLimitSeconds": 0,
        "MaxLimitSeconds": 0,
        "CountLimit": 1,
        "MinLimitMult": 2678400,
        "MaxLimitMult": 2678400,
        "LimitExpireSeconds": 2678400,
        "LootTagValuePerCount": null,
        "LootTagValueOverrideAtLimit": "",
        "LimitNotificationLocTag": ""
    },
    {
        "LootLimitID": "BagofEarthGiftsLVL1",
        "IsReplicated": false,
        "MinLimitSeconds": 0,
        "MaxLimitSeconds": 0,
        "CountLimit": 3,
        "MinLimitMult": 64800,
        "MaxLimitMult": 64800,
        "LimitExpireSeconds": 64800,
        "LootTagValuePerCount": null,
        "LootTagValueOverrideAtLimit": "",
        "LimitNotificationLocTag": ""
    },
    {
        "LootLimitID": "BagofEarthGiftsLVL10",
        "IsReplicated": false,
        "MinLimitSeconds": 0,
        "MaxLimitSeconds": 0,
        "CountLimit": 3,
        "MinLimitMult": 64800,
        "MaxLimitMult": 64800,
        "LimitExpireSeconds": 64800,
        "LootTagValuePerCount": null,
        "LootTagValueOverrideAtLimit": "",
        "LimitNotificationLocTag": ""
    },
    {
        "LootLimitID": "BagofEarthGiftsLVL20",
        "IsReplicated": false,
        "MinLimitSeconds": 0,
        "MaxLimitSeconds": 0,
        "CountLimit": 3,
        "MinLimitMult": 64800,
        "MaxLimitMult": 64800,
        "LimitExpireSeconds": 64800,
        "LootTagValuePerCount": null,
        "LootTagValueOverrideAtLimit": "",
        "LimitNotificationLocTag": ""
    },
    {
        "LootLimitID": "BagofEarthGiftsLVL30",
        "IsReplicated": false,
        "MinLimitSeconds": 0,
        "MaxLimitSeconds": 0,
        "CountLimit": 3,
        "MinLimitMult": 64800,
        "MaxLimitMult": 64800,
        "LimitExpireSeconds": 64800,
        "LootTagValuePerCount": null,
        "LootTagValueOverrideAtLimit": "",
        "LimitNotificationLocTag": ""
    },
    {
        "LootLimitID": "BagofEarthGiftsLVL40",
        "IsReplicated": false,
        "MinLimitSeconds": 0,
        "MaxLimitSeconds": 0,
        "CountLimit": 3,
        "MinLimitMult": 64800,
        "MaxLimitMult": 64800,
        "LimitExpireSeconds": 64800,
        "LootTagValuePerCount": null,
        "LootTagValueOverrideAtLimit": "",
        "LimitNotificationLocTag": ""
    },
    {
        "LootLimitID": "BagofEarthGiftsLVL50",
        "IsReplicated": false,
        "MinLimitSeconds": 0,
        "MaxLimitSeconds": 0,
        "CountLimit": 3,
        "MinLimitMult": 64800,
        "MaxLimitMult": 64800,
        "LimitExpireSeconds": 64800,
        "LootTagValuePerCount": null,
        "LootTagValueOverrideAtLimit": "",
        "LimitNotificationLocTag": ""
    },
    {
        "LootLimitID": "BagofEarthGiftsLVL60",
        "IsReplicated": false,
        "MinLimitSeconds": 0,
        "MaxLimitSeconds": 0,
        "CountLimit": 3,
        "MinLimitMult": 64800,
        "MaxLimitMult": 64800,
        "LimitExpireSeconds": 64800,
        "LootTagValuePerCount": null,
        "LootTagValueOverrideAtLimit": "",
        "LimitNotificationLocTag": ""
    },
    {
        "LootLimitID": "DarknessCoinBag",
        "IsReplicated": false,
        "MinLimitSeconds": 0,
        "MaxLimitSeconds": 0,
        "CountLimit": 2,
        "MinLimitMult": 64800,
        "MaxLimitMult": 64800,
        "LimitExpireSeconds": 64800,
        "LootTagValuePerCount": null,
        "LootTagValueOverrideAtLimit": "",
        "LimitNotificationLocTag": ""
    },
    {
        "LootLimitID": "PvP_FortTakeover_Limit",
        "IsReplicated": false,
        "MinLimitSeconds": 0,
        "MaxLimitSeconds": 0,
        "CountLimit": 10,
        "MinLimitMult": 86400,
        "MaxLimitMult": 86400,
        "LimitExpireSeconds": 86400,
        "LootTagValuePerCount": null,
        "LootTagValueOverrideAtLimit": "",
        "LimitNotificationLocTag": "@ui_reached_max_fort_takeover_rewards"
    },
    {
        "LootLimitID": "SoloShard",
        "IsReplicated": false,
        "MinLimitSeconds": 0,
        "MaxLimitSeconds": 0,
        "CountLimit": 1,
        "MinLimitMult": 86400,
        "MaxLimitMult": 86400,
        "LimitExpireSeconds": 86400,
        "LootTagValuePerCount": null,
        "LootTagValueOverrideAtLimit": "",
        "LimitNotificationLocTag": ""
    },
    {
        "LootLimitID": "Arena3v3_Limit",
        "IsReplicated": false,
        "MinLimitSeconds": 0,
        "MaxLimitSeconds": 0,
        "CountLimit": 40,
        "MinLimitMult": 86400,
        "MaxLimitMult": 86400,
        "LimitExpireSeconds": 86400,
        "LootTagValuePerCount": null,
        "LootTagValueOverrideAtLimit": "",
        "LimitNotificationLocTag": "@ui_reached_max_daily_pvp_arena_reward"
    },
    {
        "LootLimitID": "1hSkinningKnifeT5_TurkeyTerror",
        "IsReplicated": false,
        "MinLimitSeconds": 0,
        "MaxLimitSeconds": 0,
        "CountLimit": 1,
        "MinLimitMult": 2678400,
        "MaxLimitMult": 2678400,
        "LimitExpireSeconds": 2678400,
        "LootTagValuePerCount": null,
        "LootTagValueOverrideAtLimit": "",
        "LimitNotificationLocTag": ""
    },
    {
        "LootLimitID": "CoatingBeastTurkeyT5",
        "IsReplicated": false,
        "MinLimitSeconds": 0,
        "MaxLimitSeconds": 0,
        "CountLimit": 5,
        "MinLimitMult": 86400,
        "MaxLimitMult": 86400,
        "LimitExpireSeconds": 86400,
        "LootTagValuePerCount": null,
        "LootTagValueOverrideAtLimit": "",
        "LimitNotificationLocTag": ""
    },
    {
        "LootLimitID": "PotionFamilyWardBeastTurkeyT5",
        "IsReplicated": false,
        "MinLimitSeconds": 0,
        "MaxLimitSeconds": 0,
        "CountLimit": 5,
        "MinLimitMult": 86400,
        "MaxLimitMult": 86400,
        "LimitExpireSeconds": 86400,
        "LootTagValuePerCount": null,
        "LootTagValueOverrideAtLimit": "",
        "LimitNotificationLocTag": ""
    },
    {
        "LootLimitID": "MassiveTurkeyLegT5",
        "IsReplicated": false,
        "MinLimitSeconds": 0,
        "MaxLimitSeconds": 0,
        "CountLimit": 5,
        "MinLimitMult": 86400,
        "MaxLimitMult": 86400,
        "LimitExpireSeconds": 86400,
        "LootTagValuePerCount": null,
        "LootTagValueOverrideAtLimit": "",
        "LimitNotificationLocTag": ""
    },
    {
        "LootLimitID": "House_HousingItem_Buff_SPECIAL_Food_TurkeyTerror_T1",
        "IsReplicated": false,
        "MinLimitSeconds": 0,
        "MaxLimitSeconds": 0,
        "CountLimit": 1,
        "MinLimitMult": 2678400,
        "MaxLimitMult": 2678400,
        "LimitExpireSeconds": 2678400,
        "LootTagValuePerCount": null,
        "LootTagValueOverrideAtLimit": "",
        "LimitNotificationLocTag": ""
    },
    {
        "LootLimitID": "House_HousingItem_Pet_Holiday_Turkey_Pilgrim",
        "IsReplicated": false,
        "MinLimitSeconds": 0,
        "MaxLimitSeconds": 0,
        "CountLimit": 1,
        "MinLimitMult": 2678400,
        "MaxLimitMult": 2678400,
        "LimitExpireSeconds": 2678400,
        "LootTagValuePerCount": null,
        "LootTagValueOverrideAtLimit": "",
        "LimitNotificationLocTag": ""
    },
    {
        "LootLimitID": "House_HousingItem_Chair_HolidayTurkey2022_EggStool01",
        "IsReplicated": false,
        "MinLimitSeconds": 0,
        "MaxLimitSeconds": 0,
        "CountLimit": 1,
        "MinLimitMult": 604800,
        "MaxLimitMult": 604800,
        "LimitExpireSeconds": 604800,
        "LootTagValuePerCount": null,
        "LootTagValueOverrideAtLimit": "",
        "LimitNotificationLocTag": ""
    },
    {
        "LootLimitID": "Skin_Feet_TurkeyTerror_Box",
        "IsReplicated": false,
        "MinLimitSeconds": 0,
        "MaxLimitSeconds": 0,
        "CountLimit": 1,
        "MinLimitMult": 2678400,
        "MaxLimitMult": 2678400,
        "LimitExpireSeconds": 2678400,
        "LootTagValuePerCount": null,
        "LootTagValueOverrideAtLimit": "",
        "LimitNotificationLocTag": ""
    },
    {
        "LootLimitID": "Kill_TerrorTurkey",
        "IsReplicated": false,
        "MinLimitSeconds": 0,
        "MaxLimitSeconds": 0,
        "CountLimit": 15,
        "MinLimitMult": 2678400,
        "MaxLimitMult": 2678400,
        "LimitExpireSeconds": 2678400,
        "LootTagValuePerCount": null,
        "LootTagValueOverrideAtLimit": "",
        "LimitNotificationLocTag": ""
    },
    {
        "LootLimitID": "ConcealedVaultLVL1",
        "IsReplicated": false,
        "MinLimitSeconds": 0,
        "MaxLimitSeconds": 0,
        "CountLimit": 3,
        "MinLimitMult": 64800,
        "MaxLimitMult": 64800,
        "LimitExpireSeconds": 64800,
        "LootTagValuePerCount": null,
        "LootTagValueOverrideAtLimit": "",
        "LimitNotificationLocTag": ""
    },
    {
        "LootLimitID": "ConcealedVaultLVL10",
        "IsReplicated": false,
        "MinLimitSeconds": 0,
        "MaxLimitSeconds": 0,
        "CountLimit": 3,
        "MinLimitMult": 64800,
        "MaxLimitMult": 64800,
        "LimitExpireSeconds": 64800,
        "LootTagValuePerCount": null,
        "LootTagValueOverrideAtLimit": "",
        "LimitNotificationLocTag": ""
    },
    {
        "LootLimitID": "ConcealedVaultLVL20",
        "IsReplicated": false,
        "MinLimitSeconds": 0,
        "MaxLimitSeconds": 0,
        "CountLimit": 3,
        "MinLimitMult": 64800,
        "MaxLimitMult": 64800,
        "LimitExpireSeconds": 64800,
        "LootTagValuePerCount": null,
        "LootTagValueOverrideAtLimit": "",
        "LimitNotificationLocTag": ""
    },
    {
        "LootLimitID": "ConcealedVaultLVL30",
        "IsReplicated": false,
        "MinLimitSeconds": 0,
        "MaxLimitSeconds": 0,
        "CountLimit": 3,
        "MinLimitMult": 64800,
        "MaxLimitMult": 64800,
        "LimitExpireSeconds": 64800,
        "LootTagValuePerCount": null,
        "LootTagValueOverrideAtLimit": "",
        "LimitNotificationLocTag": ""
    },
    {
        "LootLimitID": "ConcealedVaultLVL40",
        "IsReplicated": false,
        "MinLimitSeconds": 0,
        "MaxLimitSeconds": 0,
        "CountLimit": 3,
        "MinLimitMult": 64800,
        "MaxLimitMult": 64800,
        "LimitExpireSeconds": 64800,
        "LootTagValuePerCount": null,
        "LootTagValueOverrideAtLimit": "",
        "LimitNotificationLocTag": ""
    },
    {
        "LootLimitID": "ConcealedVaultLVL50",
        "IsReplicated": false,
        "MinLimitSeconds": 0,
        "MaxLimitSeconds": 0,
        "CountLimit": 3,
        "MinLimitMult": 64800,
        "MaxLimitMult": 64800,
        "LimitExpireSeconds": 64800,
        "LootTagValuePerCount": null,
        "LootTagValueOverrideAtLimit": "",
        "LimitNotificationLocTag": ""
    },
    {
        "LootLimitID": "ConcealedVaultLVL60",
        "IsReplicated": false,
        "MinLimitSeconds": 0,
        "MaxLimitSeconds": 0,
        "CountLimit": 3,
        "MinLimitMult": 64800,
        "MaxLimitMult": 64800,
        "LimitExpireSeconds": 64800,
        "LootTagValuePerCount": null,
        "LootTagValueOverrideAtLimit": "",
        "LimitNotificationLocTag": ""
    },
    {
        "LootLimitID": "TurkeyTerrorCoinBagLVL1",
        "IsReplicated": false,
        "MinLimitSeconds": 0,
        "MaxLimitSeconds": 0,
        "CountLimit": 3,
        "MinLimitMult": 64800,
        "MaxLimitMult": 64800,
        "LimitExpireSeconds": 64800,
        "LootTagValuePerCount": null,
        "LootTagValueOverrideAtLimit": "",
        "LimitNotificationLocTag": ""
    },
    {
        "LootLimitID": "TurkeyTerrorCoinBagLVL10",
        "IsReplicated": false,
        "MinLimitSeconds": 0,
        "MaxLimitSeconds": 0,
        "CountLimit": 3,
        "MinLimitMult": 64800,
        "MaxLimitMult": 64800,
        "LimitExpireSeconds": 64800,
        "LootTagValuePerCount": null,
        "LootTagValueOverrideAtLimit": "",
        "LimitNotificationLocTag": ""
    },
    {
        "LootLimitID": "TurkeyTerrorCoinBagLVL20",
        "IsReplicated": false,
        "MinLimitSeconds": 0,
        "MaxLimitSeconds": 0,
        "CountLimit": 3,
        "MinLimitMult": 64800,
        "MaxLimitMult": 64800,
        "LimitExpireSeconds": 64800,
        "LootTagValuePerCount": null,
        "LootTagValueOverrideAtLimit": "",
        "LimitNotificationLocTag": ""
    },
    {
        "LootLimitID": "TurkeyTerrorCoinBagLVL30",
        "IsReplicated": false,
        "MinLimitSeconds": 0,
        "MaxLimitSeconds": 0,
        "CountLimit": 3,
        "MinLimitMult": 64800,
        "MaxLimitMult": 64800,
        "LimitExpireSeconds": 64800,
        "LootTagValuePerCount": null,
        "LootTagValueOverrideAtLimit": "",
        "LimitNotificationLocTag": ""
    },
    {
        "LootLimitID": "TurkeyTerrorCoinBagLVL40",
        "IsReplicated": false,
        "MinLimitSeconds": 0,
        "MaxLimitSeconds": 0,
        "CountLimit": 3,
        "MinLimitMult": 64800,
        "MaxLimitMult": 64800,
        "LimitExpireSeconds": 64800,
        "LootTagValuePerCount": null,
        "LootTagValueOverrideAtLimit": "",
        "LimitNotificationLocTag": ""
    },
    {
        "LootLimitID": "TurkeyTerrorCoinBagLVL50",
        "IsReplicated": false,
        "MinLimitSeconds": 0,
        "MaxLimitSeconds": 0,
        "CountLimit": 3,
        "MinLimitMult": 64800,
        "MaxLimitMult": 64800,
        "LimitExpireSeconds": 64800,
        "LootTagValuePerCount": null,
        "LootTagValueOverrideAtLimit": "",
        "LimitNotificationLocTag": ""
    },
    {
        "LootLimitID": "TurkeyTerrorCoinBagLVL60",
        "IsReplicated": false,
        "MinLimitSeconds": 0,
        "MaxLimitSeconds": 0,
        "CountLimit": 3,
        "MinLimitMult": 64800,
        "MaxLimitMult": 64800,
        "LimitExpireSeconds": 64800,
        "LootTagValuePerCount": null,
        "LootTagValueOverrideAtLimit": "",
        "LimitNotificationLocTag": ""
    },
    {
        "LootLimitID": "NightveilCoinBagLVL1",
        "IsReplicated": false,
        "MinLimitSeconds": 0,
        "MaxLimitSeconds": 0,
        "CountLimit": 3,
        "MinLimitMult": 64800,
        "MaxLimitMult": 64800,
        "LimitExpireSeconds": 64800,
        "LootTagValuePerCount": null,
        "LootTagValueOverrideAtLimit": "",
        "LimitNotificationLocTag": ""
    },
    {
        "LootLimitID": "NightveilCoinBagLVL10",
        "IsReplicated": false,
        "MinLimitSeconds": 0,
        "MaxLimitSeconds": 0,
        "CountLimit": 3,
        "MinLimitMult": 64800,
        "MaxLimitMult": 64800,
        "LimitExpireSeconds": 64800,
        "LootTagValuePerCount": null,
        "LootTagValueOverrideAtLimit": "",
        "LimitNotificationLocTag": ""
    },
    {
        "LootLimitID": "NightveilCoinBagLVL20",
        "IsReplicated": false,
        "MinLimitSeconds": 0,
        "MaxLimitSeconds": 0,
        "CountLimit": 3,
        "MinLimitMult": 64800,
        "MaxLimitMult": 64800,
        "LimitExpireSeconds": 64800,
        "LootTagValuePerCount": null,
        "LootTagValueOverrideAtLimit": "",
        "LimitNotificationLocTag": ""
    },
    {
        "LootLimitID": "NightveilCoinBagLVL30",
        "IsReplicated": false,
        "MinLimitSeconds": 0,
        "MaxLimitSeconds": 0,
        "CountLimit": 3,
        "MinLimitMult": 64800,
        "MaxLimitMult": 64800,
        "LimitExpireSeconds": 64800,
        "LootTagValuePerCount": null,
        "LootTagValueOverrideAtLimit": "",
        "LimitNotificationLocTag": ""
    },
    {
        "LootLimitID": "NightveilCoinBagLVL40",
        "IsReplicated": false,
        "MinLimitSeconds": 0,
        "MaxLimitSeconds": 0,
        "CountLimit": 3,
        "MinLimitMult": 64800,
        "MaxLimitMult": 64800,
        "LimitExpireSeconds": 64800,
        "LootTagValuePerCount": null,
        "LootTagValueOverrideAtLimit": "",
        "LimitNotificationLocTag": ""
    },
    {
        "LootLimitID": "NightveilCoinBagLVL50",
        "IsReplicated": false,
        "MinLimitSeconds": 0,
        "MaxLimitSeconds": 0,
        "CountLimit": 3,
        "MinLimitMult": 64800,
        "MaxLimitMult": 64800,
        "LimitExpireSeconds": 64800,
        "LootTagValuePerCount": null,
        "LootTagValueOverrideAtLimit": "",
        "LimitNotificationLocTag": ""
    },
    {
        "LootLimitID": "NightveilCoinBagLVL60",
        "IsReplicated": false,
        "MinLimitSeconds": 0,
        "MaxLimitSeconds": 0,
        "CountLimit": 3,
        "MinLimitMult": 64800,
        "MaxLimitMult": 64800,
        "LimitExpireSeconds": 64800,
        "LootTagValuePerCount": null,
        "LootTagValueOverrideAtLimit": "",
        "LimitNotificationLocTag": ""
    },
    {
        "LootLimitID": "GoldenScarab",
        "IsReplicated": false,
        "MinLimitSeconds": 0,
        "MaxLimitSeconds": 0,
        "CountLimit": 10,
        "MinLimitMult": 86400,
        "MaxLimitMult": 86400,
        "LimitExpireSeconds": 86400,
        "LootTagValuePerCount": null,
        "LootTagValueOverrideAtLimit": "",
        "LimitNotificationLocTag": ""
    },
    {
        "LootLimitID": "Cooking_music_box",
        "IsReplicated": false,
        "MinLimitSeconds": 0,
        "MaxLimitSeconds": 0,
        "CountLimit": 1,
        "MinLimitMult": 64800,
        "MaxLimitMult": 64800,
        "LimitExpireSeconds": 64800,
        "LootTagValuePerCount": null,
        "LootTagValueOverrideAtLimit": "",
        "LimitNotificationLocTag": ""
    },
    {
        "LootLimitID": "Loom_music_box",
        "IsReplicated": false,
        "MinLimitSeconds": 0,
        "MaxLimitSeconds": 0,
        "CountLimit": 1,
        "MinLimitMult": 64800,
        "MaxLimitMult": 64800,
        "LimitExpireSeconds": 64800,
        "LootTagValuePerCount": null,
        "LootTagValueOverrideAtLimit": "",
        "LimitNotificationLocTag": ""
    },
    {
        "LootLimitID": "Furnishing_music_box",
        "IsReplicated": false,
        "MinLimitSeconds": 0,
        "MaxLimitSeconds": 0,
        "CountLimit": 1,
        "MinLimitMult": 64800,
        "MaxLimitMult": 64800,
        "LimitExpireSeconds": 64800,
        "LootTagValuePerCount": null,
        "LootTagValueOverrideAtLimit": "",
        "LimitNotificationLocTag": ""
    },
    {
        "LootLimitID": "WoodenCoin",
        "IsReplicated": false,
        "MinLimitSeconds": 0,
        "MaxLimitSeconds": 0,
        "CountLimit": 5,
        "MinLimitMult": 86400,
        "MaxLimitMult": 86400,
        "LimitExpireSeconds": 86400,
        "LootTagValuePerCount": null,
        "LootTagValueOverrideAtLimit": "",
        "LimitNotificationLocTag": ""
    },
    {
        "LootLimitID": "SportsmanSpoilsLVL1",
        "IsReplicated": false,
        "MinLimitSeconds": 0,
        "MaxLimitSeconds": 0,
        "CountLimit": 3,
        "MinLimitMult": 64800,
        "MaxLimitMult": 64800,
        "LimitExpireSeconds": 64800,
        "LootTagValuePerCount": null,
        "LootTagValueOverrideAtLimit": "",
        "LimitNotificationLocTag": ""
    },
    {
        "LootLimitID": "SportsmanSpoilsLVL10",
        "IsReplicated": false,
        "MinLimitSeconds": 0,
        "MaxLimitSeconds": 0,
        "CountLimit": 3,
        "MinLimitMult": 64800,
        "MaxLimitMult": 64800,
        "LimitExpireSeconds": 64800,
        "LootTagValuePerCount": null,
        "LootTagValueOverrideAtLimit": "",
        "LimitNotificationLocTag": ""
    },
    {
        "LootLimitID": "SportsmanSpoilsLVL20",
        "IsReplicated": false,
        "MinLimitSeconds": 0,
        "MaxLimitSeconds": 0,
        "CountLimit": 3,
        "MinLimitMult": 64800,
        "MaxLimitMult": 64800,
        "LimitExpireSeconds": 64800,
        "LootTagValuePerCount": null,
        "LootTagValueOverrideAtLimit": "",
        "LimitNotificationLocTag": ""
    },
    {
        "LootLimitID": "SportsmanSpoilsLVL30",
        "IsReplicated": false,
        "MinLimitSeconds": 0,
        "MaxLimitSeconds": 0,
        "CountLimit": 3,
        "MinLimitMult": 64800,
        "MaxLimitMult": 64800,
        "LimitExpireSeconds": 64800,
        "LootTagValuePerCount": null,
        "LootTagValueOverrideAtLimit": "",
        "LimitNotificationLocTag": ""
    },
    {
        "LootLimitID": "SportsmanSpoilsLVL40",
        "IsReplicated": false,
        "MinLimitSeconds": 0,
        "MaxLimitSeconds": 0,
        "CountLimit": 3,
        "MinLimitMult": 64800,
        "MaxLimitMult": 64800,
        "LimitExpireSeconds": 64800,
        "LootTagValuePerCount": null,
        "LootTagValueOverrideAtLimit": "",
        "LimitNotificationLocTag": ""
    },
    {
        "LootLimitID": "SportsmanSpoilsLVL50",
        "IsReplicated": false,
        "MinLimitSeconds": 0,
        "MaxLimitSeconds": 0,
        "CountLimit": 3,
        "MinLimitMult": 64800,
        "MaxLimitMult": 64800,
        "LimitExpireSeconds": 64800,
        "LootTagValuePerCount": null,
        "LootTagValueOverrideAtLimit": "",
        "LimitNotificationLocTag": ""
    },
    {
        "LootLimitID": "SportsmanSpoilsLVL60",
        "IsReplicated": false,
        "MinLimitSeconds": 0,
        "MaxLimitSeconds": 0,
        "CountLimit": 3,
        "MinLimitMult": 64800,
        "MaxLimitMult": 64800,
        "LimitExpireSeconds": 64800,
        "LootTagValuePerCount": null,
        "LootTagValueOverrideAtLimit": "",
        "LimitNotificationLocTag": ""
    },
    {
        "LootLimitID": "SpringtideCoinBagLVL1",
        "IsReplicated": false,
        "MinLimitSeconds": 0,
        "MaxLimitSeconds": 0,
        "CountLimit": 4,
        "MinLimitMult": 64800,
        "MaxLimitMult": 64800,
        "LimitExpireSeconds": 64800,
        "LootTagValuePerCount": null,
        "LootTagValueOverrideAtLimit": "",
        "LimitNotificationLocTag": ""
    },
    {
        "LootLimitID": "SpringtideCoinBagLVL10",
        "IsReplicated": false,
        "MinLimitSeconds": 0,
        "MaxLimitSeconds": 0,
        "CountLimit": 4,
        "MinLimitMult": 64800,
        "MaxLimitMult": 64800,
        "LimitExpireSeconds": 64800,
        "LootTagValuePerCount": null,
        "LootTagValueOverrideAtLimit": "",
        "LimitNotificationLocTag": ""
    },
    {
        "LootLimitID": "SpringtideCoinBagLVL20",
        "IsReplicated": false,
        "MinLimitSeconds": 0,
        "MaxLimitSeconds": 0,
        "CountLimit": 4,
        "MinLimitMult": 64800,
        "MaxLimitMult": 64800,
        "LimitExpireSeconds": 64800,
        "LootTagValuePerCount": null,
        "LootTagValueOverrideAtLimit": "",
        "LimitNotificationLocTag": ""
    },
    {
        "LootLimitID": "SpringtideCoinBagLVL30",
        "IsReplicated": false,
        "MinLimitSeconds": 0,
        "MaxLimitSeconds": 0,
        "CountLimit": 4,
        "MinLimitMult": 64800,
        "MaxLimitMult": 64800,
        "LimitExpireSeconds": 64800,
        "LootTagValuePerCount": null,
        "LootTagValueOverrideAtLimit": "",
        "LimitNotificationLocTag": ""
    },
    {
        "LootLimitID": "SpringtideCoinBagLVL40",
        "IsReplicated": false,
        "MinLimitSeconds": 0,
        "MaxLimitSeconds": 0,
        "CountLimit": 4,
        "MinLimitMult": 64800,
        "MaxLimitMult": 64800,
        "LimitExpireSeconds": 64800,
        "LootTagValuePerCount": null,
        "LootTagValueOverrideAtLimit": "",
        "LimitNotificationLocTag": ""
    },
    {
        "LootLimitID": "SpringtideCoinBagLVL50",
        "IsReplicated": false,
        "MinLimitSeconds": 0,
        "MaxLimitSeconds": 0,
        "CountLimit": 4,
        "MinLimitMult": 64800,
        "MaxLimitMult": 64800,
        "LimitExpireSeconds": 64800,
        "LootTagValuePerCount": null,
        "LootTagValueOverrideAtLimit": "",
        "LimitNotificationLocTag": ""
    },
    {
        "LootLimitID": "SpringtideCoinBagLVL60",
        "IsReplicated": false,
        "MinLimitSeconds": 0,
        "MaxLimitSeconds": 0,
        "CountLimit": 4,
        "MinLimitMult": 64800,
        "MaxLimitMult": 64800,
        "LimitExpireSeconds": 64800,
        "LootTagValuePerCount": null,
        "LootTagValueOverrideAtLimit": "",
        "LimitNotificationLocTag": ""
    },
    {
        "LootLimitID": "Spring_Prismabloom_Token_Limit",
        "IsReplicated": false,
        "MinLimitSeconds": 0,
        "MaxLimitSeconds": 0,
        "CountLimit": 10,
        "MinLimitMult": 64800,
        "MaxLimitMult": 64800,
        "LimitExpireSeconds": 64800,
        "LootTagValuePerCount": null,
        "LootTagValueOverrideAtLimit": "",
        "LimitNotificationLocTag": ""
    },
    {
        "LootLimitID": "Spring_Prismabloom_Premium_Limit",
        "IsReplicated": false,
        "MinLimitSeconds": 0,
        "MaxLimitSeconds": 0,
        "CountLimit": 1,
        "MinLimitMult": 64800,
        "MaxLimitMult": 64800,
        "LimitExpireSeconds": 64800,
        "LootTagValuePerCount": null,
        "LootTagValueOverrideAtLimit": "",
        "LimitNotificationLocTag": ""
    },
    {
        "LootLimitID": "Skin_Mask_RabbitSeason_Box",
        "IsReplicated": false,
        "MinLimitSeconds": 0,
        "MaxLimitSeconds": 0,
        "CountLimit": 1,
        "MinLimitMult": 2678400,
        "MaxLimitMult": 2678400,
        "LimitExpireSeconds": 2678400,
        "LootTagValuePerCount": null,
        "LootTagValueOverrideAtLimit": "",
        "LimitNotificationLocTag": ""
    },
    {
        "LootLimitID": "House_HousingItem_Buff_Damage_Vs_Ancients_T0",
        "IsReplicated": false,
        "MinLimitSeconds": 0,
        "MaxLimitSeconds": 0,
        "CountLimit": 1,
        "MinLimitMult": 64800,
        "MaxLimitMult": 64800,
        "LimitExpireSeconds": 64800,
        "LootTagValuePerCount": null,
        "LootTagValueOverrideAtLimit": "",
        "LimitNotificationLocTag": ""
    },
    {
        "LootLimitID": "House_HousingItem_Buff_Damage_Vs_Beasts_T0",
        "IsReplicated": false,
        "MinLimitSeconds": 0,
        "MaxLimitSeconds": 0,
        "CountLimit": 1,
        "MinLimitMult": 64800,
        "MaxLimitMult": 64800,
        "LimitExpireSeconds": 64800,
        "LootTagValuePerCount": null,
        "LootTagValueOverrideAtLimit": "",
        "LimitNotificationLocTag": ""
    },
    {
        "LootLimitID": "House_HousingItem_Buff_Damage_Vs_Corrupted_T0",
        "IsReplicated": false,
        "MinLimitSeconds": 0,
        "MaxLimitSeconds": 0,
        "CountLimit": 1,
        "MinLimitMult": 64800,
        "MaxLimitMult": 64800,
        "LimitExpireSeconds": 64800,
        "LootTagValuePerCount": null,
        "LootTagValueOverrideAtLimit": "",
        "LimitNotificationLocTag": ""
    },
    {
        "LootLimitID": "House_HousingItem_Buff_Damage_Vs_Lost_T0",
        "IsReplicated": false,
        "MinLimitSeconds": 0,
        "MaxLimitSeconds": 0,
        "CountLimit": 1,
        "MinLimitMult": 64800,
        "MaxLimitMult": 64800,
        "LimitExpireSeconds": 64800,
        "LootTagValuePerCount": null,
        "LootTagValueOverrideAtLimit": "",
        "LimitNotificationLocTag": ""
    },
    {
        "LootLimitID": "WorldEvent_S1_BonusBox",
        "IsReplicated": false,
        "MinLimitSeconds": 0,
        "MaxLimitSeconds": 0,
        "CountLimit": 3,
        "MinLimitMult": 64800,
        "MaxLimitMult": 64800,
        "LimitExpireSeconds": 64800,
        "LootTagValuePerCount": null,
        "LootTagValueOverrideAtLimit": "",
        "LimitNotificationLocTag": ""
    },
    {
        "LootLimitID": "Schematic_House_HousingItem_Season1_SprigganFlameBrazier",
        "IsReplicated": false,
        "MinLimitSeconds": 0,
        "MaxLimitSeconds": 0,
        "CountLimit": 1,
        "MinLimitMult": 1209600,
        "MaxLimitMult": 1209600,
        "LimitExpireSeconds": 1209600,
        "LootTagValuePerCount": null,
        "LootTagValueOverrideAtLimit": "",
        "LimitNotificationLocTag": ""
    },
    {
        "LootLimitID": "Tag_S1Event_PityTicker",
        "IsReplicated": false,
        "MinLimitSeconds": 0,
        "MaxLimitSeconds": 0,
        "CountLimit": 42,
        "MinLimitMult": 1209600,
        "MaxLimitMult": 1209600,
        "LimitExpireSeconds": 1209600,
        "LootTagValuePerCount": 1,
        "LootTagValueOverrideAtLimit": "",
        "LimitNotificationLocTag": ""
    },
    {
        "LootLimitID": "2hWarhammer_MountainShakerT5",
        "IsReplicated": false,
        "MinLimitSeconds": 64800,
        "MaxLimitSeconds": 64800,
        "CountLimit": 2,
        "MinLimitMult": 1209600,
        "MaxLimitMult": 1209600,
        "LimitExpireSeconds": 1209600,
        "LootTagValuePerCount": null,
        "LootTagValueOverrideAtLimit": "",
        "LimitNotificationLocTag": ""
    },
    {
        "LootLimitID": "2hMusket_BurnweaverT5",
        "IsReplicated": false,
        "MinLimitSeconds": 64800,
        "MaxLimitSeconds": 64800,
        "CountLimit": 2,
        "MinLimitMult": 1209600,
        "MaxLimitMult": 1209600,
        "LimitExpireSeconds": 1209600,
        "LootTagValuePerCount": null,
        "LootTagValueOverrideAtLimit": "",
        "LimitNotificationLocTag": ""
    },
    {
        "LootLimitID": "2hSpear_BlazingBushHookT5",
        "IsReplicated": false,
        "MinLimitSeconds": 64800,
        "MaxLimitSeconds": 64800,
        "CountLimit": 2,
        "MinLimitMult": 1209600,
        "MaxLimitMult": 1209600,
        "LimitExpireSeconds": 1209600,
        "LootTagValuePerCount": null,
        "LootTagValueOverrideAtLimit": "",
        "LimitNotificationLocTag": ""
    },
    {
        "LootLimitID": "1hGauntletVoid_ForestsShadowT5",
        "IsReplicated": false,
        "MinLimitSeconds": 64800,
        "MaxLimitSeconds": 64800,
        "CountLimit": 2,
        "MinLimitMult": 1209600,
        "MaxLimitMult": 1209600,
        "LimitExpireSeconds": 1209600,
        "LootTagValuePerCount": null,
        "LootTagValueOverrideAtLimit": "",
        "LimitNotificationLocTag": ""
    },
    {
        "LootLimitID": "LightHead_BramblehelmT5",
        "IsReplicated": false,
        "MinLimitSeconds": 64800,
        "MaxLimitSeconds": 64800,
        "CountLimit": 2,
        "MinLimitMult": 1209600,
        "MaxLimitMult": 1209600,
        "LimitExpireSeconds": 1209600,
        "LootTagValuePerCount": null,
        "LootTagValueOverrideAtLimit": "",
        "LimitNotificationLocTag": ""
    },
    {
        "LootLimitID": "LightLegs_TrailblazersLegGuardsT5",
        "IsReplicated": false,
        "MinLimitSeconds": 64800,
        "MaxLimitSeconds": 64800,
        "CountLimit": 2,
        "MinLimitMult": 1209600,
        "MaxLimitMult": 1209600,
        "LimitExpireSeconds": 1209600,
        "LootTagValuePerCount": null,
        "LootTagValueOverrideAtLimit": "",
        "LimitNotificationLocTag": ""
    },
    {
        "LootLimitID": "WorldEvent_Crassus_BonusBox",
        "IsReplicated": false,
        "MinLimitSeconds": 0,
        "MaxLimitSeconds": 0,
        "CountLimit": 1,
        "MinLimitMult": 64800,
        "MaxLimitMult": 64800,
        "LimitExpireSeconds": 64800,
        "LootTagValuePerCount": null,
        "LootTagValueOverrideAtLimit": "",
        "LimitNotificationLocTag": ""
    },
    {
        "LootLimitID": "Tag_RabbitEvent_PityTicker",
        "IsReplicated": false,
        "MinLimitSeconds": 0,
        "MaxLimitSeconds": 0,
        "CountLimit": 400,
        "MinLimitMult": 2678400,
        "MaxLimitMult": 2678400,
        "LimitExpireSeconds": 2678400,
        "LootTagValuePerCount": 1,
        "LootTagValueOverrideAtLimit": "",
        "LimitNotificationLocTag": ""
    },
    {
        "LootLimitID": "2hGreataxe_HugoT5",
        "IsReplicated": false,
        "MinLimitSeconds": 0,
        "MaxLimitSeconds": 0,
        "CountLimit": 1,
        "MinLimitMult": 2678400,
        "MaxLimitMult": 2678400,
        "LimitExpireSeconds": 2678400,
        "LootTagValuePerCount": null,
        "LootTagValueOverrideAtLimit": "",
        "LimitNotificationLocTag": ""
    },
    {
        "LootLimitID": "2hGreatSword_HugoT5",
        "IsReplicated": false,
        "MinLimitSeconds": 0,
        "MaxLimitSeconds": 0,
        "CountLimit": 1,
        "MinLimitMult": 2678400,
        "MaxLimitMult": 2678400,
        "LimitExpireSeconds": 2678400,
        "LootTagValuePerCount": null,
        "LootTagValueOverrideAtLimit": "",
        "LimitNotificationLocTag": ""
    },
    {
        "LootLimitID": "2hBow_BrevisT5",
        "IsReplicated": false,
        "MinLimitSeconds": 0,
        "MaxLimitSeconds": 0,
        "CountLimit": 1,
        "MinLimitMult": 2678400,
        "MaxLimitMult": 2678400,
        "LimitExpireSeconds": 2678400,
        "LootTagValuePerCount": null,
        "LootTagValueOverrideAtLimit": "",
        "LimitNotificationLocTag": ""
    },
    {
        "LootLimitID": "2hStaffFire_BrevisT5",
        "IsReplicated": false,
        "MinLimitSeconds": 0,
        "MaxLimitSeconds": 0,
        "CountLimit": 1,
        "MinLimitMult": 2678400,
        "MaxLimitMult": 2678400,
        "LimitExpireSeconds": 2678400,
        "LootTagValuePerCount": null,
        "LootTagValueOverrideAtLimit": "",
        "LimitNotificationLocTag": ""
    },
    {
        "LootLimitID": "HeavyChest_HugoT5",
        "IsReplicated": false,
        "MinLimitSeconds": 0,
        "MaxLimitSeconds": 0,
        "CountLimit": 1,
        "MinLimitMult": 2678400,
        "MaxLimitMult": 2678400,
        "LimitExpireSeconds": 2678400,
        "LootTagValuePerCount": null,
        "LootTagValueOverrideAtLimit": "",
        "LimitNotificationLocTag": ""
    },
    {
        "LootLimitID": "HeavyHands_HugoT5",
        "IsReplicated": false,
        "MinLimitSeconds": 0,
        "MaxLimitSeconds": 0,
        "CountLimit": 1,
        "MinLimitMult": 2678400,
        "MaxLimitMult": 2678400,
        "LimitExpireSeconds": 2678400,
        "LootTagValuePerCount": null,
        "LootTagValueOverrideAtLimit": "",
        "LimitNotificationLocTag": ""
    },
    {
        "LootLimitID": "MediumHead_BrevisT5",
        "IsReplicated": false,
        "MinLimitSeconds": 0,
        "MaxLimitSeconds": 0,
        "CountLimit": 1,
        "MinLimitMult": 2678400,
        "MaxLimitMult": 2678400,
        "LimitExpireSeconds": 2678400,
        "LootTagValuePerCount": null,
        "LootTagValueOverrideAtLimit": "",
        "LimitNotificationLocTag": ""
    },
    {
        "LootLimitID": "MediumFeet_BrevisT5",
        "IsReplicated": false,
        "MinLimitSeconds": 0,
        "MaxLimitSeconds": 0,
        "CountLimit": 1,
        "MinLimitMult": 2678400,
        "MaxLimitMult": 2678400,
        "LimitExpireSeconds": 2678400,
        "LootTagValuePerCount": null,
        "LootTagValueOverrideAtLimit": "",
        "LimitNotificationLocTag": ""
    },
    {
        "LootLimitID": "Tag_LegacyofCrassus_Ticker",
        "IsReplicated": false,
        "MinLimitSeconds": 0,
        "MaxLimitSeconds": 0,
        "CountLimit": 8,
        "MinLimitMult": 2678400,
        "MaxLimitMult": 2678400,
        "LimitExpireSeconds": 2678400,
        "LootTagValuePerCount": null,
        "LootTagValueOverrideAtLimit": "",
        "LimitNotificationLocTag": ""
    },
    {
        "LootLimitID": "WorldEvent_S2_BonusBox",
        "IsReplicated": false,
        "MinLimitSeconds": 0,
        "MaxLimitSeconds": 0,
        "CountLimit": 3,
        "MinLimitMult": 64800,
        "MaxLimitMult": 64800,
        "LimitExpireSeconds": 64800,
        "LootTagValuePerCount": null,
        "LootTagValueOverrideAtLimit": "",
        "LimitNotificationLocTag": ""
    },
    {
        "LootLimitID": "Tag_S2Event_PityTicker",
        "IsReplicated": false,
        "MinLimitSeconds": 0,
        "MaxLimitSeconds": 0,
        "CountLimit": 42,
        "MinLimitMult": 1209600,
        "MaxLimitMult": 1209600,
        "LimitExpireSeconds": 1209600,
        "LootTagValuePerCount": 1,
        "LootTagValueOverrideAtLimit": "",
        "LimitNotificationLocTag": ""
    },
    {
        "LootLimitID": "Skin_Head_SandwormHat_Box",
        "IsReplicated": false,
        "MinLimitSeconds": 0,
        "MaxLimitSeconds": 0,
        "CountLimit": 1,
        "MinLimitMult": 1209600,
        "MaxLimitMult": 1209600,
        "LimitExpireSeconds": 1209600,
        "LootTagValuePerCount": null,
        "LootTagValueOverrideAtLimit": "",
        "LimitNotificationLocTag": ""
    },
    {
        "LootLimitID": "House_HousingItem_Season2_SandwormEgg_Variant4",
        "IsReplicated": false,
        "MinLimitSeconds": 0,
        "MaxLimitSeconds": 0,
        "CountLimit": 1,
        "MinLimitMult": 1209600,
        "MaxLimitMult": 1209600,
        "LimitExpireSeconds": 1209600,
        "LootTagValuePerCount": null,
        "LootTagValueOverrideAtLimit": "",
        "LimitNotificationLocTag": ""
    }
]
